colorful_test/__init__.py
colorful_test/__main__.py
colorful_test/exceptions.py
colorful_test/message.py
colorful_test/skip_test.py
colorful_test/testcase.py
colorful_test-1.0.1.dist-info/LICENSE
colorful_test-1.0.1.dist-info/METADATA
colorful_test-1.0.1.dist-info/WHEEL
colorful_test-1.0.1.dist-info/RECORD
