Metadata-Version: 2.3
Name: colorful-test
Version: 1.0.1
Summary: A unit testing framework with colorful messages.
Author: nqabenhle
Author-email: nqmlabajhb024@student.wethinkcode.co.za
Requires-Python: >=3.10,<4.0
Classifier: Programming Language :: Python :: 3
Classifier: Programming Language :: Python :: 3.10
Classifier: Programming Language :: Python :: 3.11
Classifier: Programming Language :: Python :: 3.12
Classifier: Programming Language :: Python :: 3.13
